<PAMDataset>
  <SRS>PROJCS[&quot;UTM Zone 17, Northern Hemisphere&quot;,GEOGCS[&quot;NAD83&quot;,DATUM[&quot;North_American_Datum_1983&quot;,SPHEROID[&quot;GRS 1980&quot;,6378137,298.257222101,AUTHORITY[&quot;EPSG&quot;,&quot;7019&quot;]],TOWGS84[0,0,0,0,0,0,0],AUTHORITY[&quot;EPSG&quot;,&quot;6269&quot;]],PRIMEM[&quot;Greenwich&quot;,0,AUTHORITY[&quot;EPSG&quot;,&quot;8901&quot;]],UNIT[&quot;degree&quot;,0.0174532925199433,AUTHORITY[&quot;EPSG&quot;,&quot;9108&quot;]],AXIS[&quot;Lat&quot;,NORTH],AXIS[&quot;Long&quot;,EAST],AUTHORITY[&quot;EPSG&quot;,&quot;4269&quot;]],PROJECTION[&quot;Transverse_Mercator&quot;],PARAMETER[&quot;latitude_of_origin&quot;,0],PARAMETER[&quot;central_meridian&quot;,-81],PARAMETER[&quot;scale_factor&quot;,0.9996],PARAMETER[&quot;false_easting&quot;,500000],PARAMETER[&quot;false_northing&quot;,0],UNIT[&quot;Meter&quot;,1],AUTHORITY[&quot;EPSG&quot;,&quot;26917&quot;]]</SRS>
  <GeoTransform> 7.3690264796154771e+005, 2.4396809999999998e+000, 0.0000000000000000e+000, 4.3623471955240630e+006, 0.0000000000000000e+000,-2.4396809999999829e+000</GeoTransform>
  <Metadata>
    <MDI key="IMAGE__INPUT_NAME">C:\ARC_FILES\VA_Mapping\white_hall\Rectifywhitehall.tif</MDI>
    <MDI key="IMAGE__INPUT_FILE_SIZE">26787948.000000</MDI>
    <MDI key="GEO__spref_horizsys_cordsysn_geogcsn">GCS_North_American_1983</MDI>
    <MDI key="GEO__spref_horizsys_cordsysn_projcsn">NAD_1983_UTM_Zone_17N</MDI>
    <MDI key="GEO__spref_horizsys_planar_planci_plance">row and column</MDI>
    <MDI key="GEO__spref_horizsys_planar_planci_plandu">meters</MDI>
    <MDI key="GEO__spref_horizsys_planar_planci_coordrep_absres">2.439681</MDI>
    <MDI key="GEO__spref_horizsys_planar_planci_coordrep_ordres">2.439681</MDI>
    <MDI key="GEO__spref_horizsys_planar_gridsys_gridsysn">Universal Transverse Mercator</MDI>
    <MDI key="GEO__spref_horizsys_planar_gridsys_utm_utmzone">17</MDI>
    <MDI key="GEO__spref_horizsys_planar_gridsys_utm_transmer_sfctrmer">0.999600</MDI>
    <MDI key="GEO__spref_horizsys_planar_gridsys_utm_transmer_longcm">-81.000000</MDI>
    <MDI key="GEO__spref_horizsys_planar_gridsys_utm_transmer_latprjo">0.000000</MDI>
    <MDI key="GEO__spref_horizsys_planar_gridsys_utm_transmer_feast">500000.000000</MDI>
    <MDI key="GEO__spref_horizsys_planar_gridsys_utm_transmer_fnorth">0.000000</MDI>
    <MDI key="GEO__spref_horizsys_geodetic_horizdn">North American Datum of 1983</MDI>
    <MDI key="GEO__spref_horizsys_geodetic_ellips">Geodetic Reference System 80</MDI>
    <MDI key="GEO__spref_horizsys_geodetic_semiaxis">6378137.000000</MDI>
    <MDI key="GEO__spref_horizsys_geodetic_denflat">298.257222</MDI>
    <MDI key="IMAGE__COMPRESSION_VERSION">1,6,3</MDI>
    <MDI key="IMAGE__TARGET_COMPRESSION_RATIO">10.000000</MDI>
    <MDI key="IMAGE__COMPRESSION_NLEV">8</MDI>
    <MDI key="IMAGE__COMPRESSION_WEIGHT">4.000000</MDI>
    <MDI key="IMAGE__COMPRESSION_GAMMA">2.000000</MDI>
    <MDI key="IMAGE__COMPRESSION_BLOCK_SIZE">512</MDI>
    <MDI key="IMAGE__CREATION_DATE">Fri Sep 08 10:47:23 2006
</MDI>
    <MDI key="IMAGE__NO_DITHER">0</MDI>
    <MDI key="IMAGE__WIDTH">4598</MDI>
    <MDI key="IMAGE__HEIGHT">5826</MDI>
    <MDI key="IMAGE__INPUT_LUT">0,255,0,203,131,201,137,167,255,218,207,255,255,0,203</MDI>
    <MDI key="IMAGE__NO_DATA_VALUE">200,80,228</MDI>
    <MDI key="IMAGE__TRANSPARENT_DATA_VALUE">0,0,6</MDI>
    <MDI key="IMAGE__COLOR_SCHEME">0</MDI>
    <MDI key="IMAGE__DATA_TYPE">0</MDI>
    <MDI key="IMAGE__XY_ORIGIN">736903.867802,4362345.975684</MDI>
    <MDI key="IMAGE__X_RESOLUTION">2.439681</MDI>
    <MDI key="IMAGE__Y_RESOLUTION">2.439681</MDI>
    <MDI key="VERSION">MG2</MDI>
  </Metadata>
  <PAMRasterBand band="1">
    <Histograms>
      <HistItem>
        <HistMin>-0.5</HistMin>
        <HistMax>255.5</HistMax>
        <BucketCount>256</BucketCount>
        <IncludeOutOfRange>0</IncludeOutOfRange>
        <Approximate>1</Approximate>
        <HistCounts>157|9|11|15|23|19|17|8|10|30|15|10|6|3|4|1|1|4|1|3|1|2|1|3|2|2|2|0|2|3|1|1|1|1|2|3|1|1|1|2|0|1|1|1|4|0|3|1|0|0|3|2|3|1|0|0|7|0|1|3|1|1|1|2|0|1|3|1|0|0|2|1|0|0|3|1|1|1|3|1|0|1|1|1|3|4|0|1|1|1|0|0|1|2|1|1|0|1|2|1|2|3|0|1|4|2|0|2|2|3|2|0|4|1|4|0|2|1|0|2|2|0|1|1|1|4|0|1|1|2|1|1|1|2|1|2|3|2|2|1|3|0|2|1|0|3|3|0|1|1|0|1|4|0|3|1|0|1|5|8|2|6|0|2|4|3|2|3|4|4|2|5|4|11|10|8|8|10|17|13|22|20|22|35|54|63|84|78|116|136|179|202|279|271|283|267|267|202|144|113|90|74|74|63|52|58|46|51|59|63|47|61|52|51|42|44|66|47|45|59|40|44|61|62|53|41|61|36|49|55|50|42|59|49|52|62|56|60|50|51|68|52|77|48|58|56|70|65|72|73|73|58|39|53|35|39</HistCounts>
      </HistItem>
    </Histograms>
    <GDALRasterAttributeTable>
      <FieldDefn index="0">
        <Name>Histogram</Name>
        <Type>0</Type>
        <Usage>0</Usage>
      </FieldDefn>
      <Row index="0">
        <F>1049384</F>
      </Row>
      <Row index="1">
        <F>50666</F>
      </Row>
      <Row index="2">
        <F>16317</F>
      </Row>
      <Row index="3">
        <F>17346</F>
      </Row>
      <Row index="4">
        <F>24892</F>
      </Row>
      <Row index="5">
        <F>28861</F>
      </Row>
      <Row index="6">
        <F>16807</F>
      </Row>
      <Row index="7">
        <F>4753</F>
      </Row>
      <Row index="8">
        <F>1764</F>
      </Row>
      <Row index="9">
        <F>1764</F>
      </Row>
      <Row index="10">
        <F>1372</F>
      </Row>
      <Row index="11">
        <F>1176</F>
      </Row>
      <Row index="12">
        <F>637</F>
      </Row>
      <Row index="13">
        <F>588</F>
      </Row>
      <Row index="14">
        <F>1225</F>
      </Row>
      <Row index="15">
        <F>1127</F>
      </Row>
      <Row index="16">
        <F>1617</F>
      </Row>
      <Row index="17">
        <F>1519</F>
      </Row>
      <Row index="18">
        <F>1176</F>
      </Row>
      <Row index="19">
        <F>931</F>
      </Row>
      <Row index="20">
        <F>1715</F>
      </Row>
      <Row index="21">
        <F>1470</F>
      </Row>
      <Row index="22">
        <F>931</F>
      </Row>
      <Row index="23">
        <F>686</F>
      </Row>
      <Row index="24">
        <F>784</F>
      </Row>
      <Row index="25">
        <F>637</F>
      </Row>
      <Row index="26">
        <F>441</F>
      </Row>
      <Row index="27">
        <F>441</F>
      </Row>
      <Row index="28">
        <F>294</F>
      </Row>
      <Row index="29">
        <F>441</F>
      </Row>
      <Row index="30">
        <F>588</F>
      </Row>
      <Row index="31">
        <F>784</F>
      </Row>
      <Row index="32">
        <F>735</F>
      </Row>
      <Row index="33">
        <F>882</F>
      </Row>
      <Row index="34">
        <F>1029</F>
      </Row>
      <Row index="35">
        <F>833</F>
      </Row>
      <Row index="36">
        <F>735</F>
      </Row>
      <Row index="37">
        <F>735</F>
      </Row>
      <Row index="38">
        <F>980</F>
      </Row>
      <Row index="39">
        <F>441</F>
      </Row>
      <Row index="40">
        <F>637</F>
      </Row>
      <Row index="41">
        <F>931</F>
      </Row>
      <Row index="42">
        <F>980</F>
      </Row>
      <Row index="43">
        <F>1029</F>
      </Row>
      <Row index="44">
        <F>980</F>
      </Row>
      <Row index="45">
        <F>637</F>
      </Row>
      <Row index="46">
        <F>490</F>
      </Row>
      <Row index="47">
        <F>490</F>
      </Row>
      <Row index="48">
        <F>343</F>
      </Row>
      <Row index="49">
        <F>392</F>
      </Row>
      <Row index="50">
        <F>588</F>
      </Row>
      <Row index="51">
        <F>539</F>
      </Row>
      <Row index="52">
        <F>588</F>
      </Row>
      <Row index="53">
        <F>833</F>
      </Row>
      <Row index="54">
        <F>490</F>
      </Row>
      <Row index="55">
        <F>1127</F>
      </Row>
      <Row index="56">
        <F>980</F>
      </Row>
      <Row index="57">
        <F>931</F>
      </Row>
      <Row index="58">
        <F>490</F>
      </Row>
      <Row index="59">
        <F>686</F>
      </Row>
      <Row index="60">
        <F>441</F>
      </Row>
      <Row index="61">
        <F>588</F>
      </Row>
      <Row index="62">
        <F>441</F>
      </Row>
      <Row index="63">
        <F>784</F>
      </Row>
      <Row index="64">
        <F>441</F>
      </Row>
      <Row index="65">
        <F>637</F>
      </Row>
      <Row index="66">
        <F>343</F>
      </Row>
      <Row index="67">
        <F>637</F>
      </Row>
      <Row index="68">
        <F>882</F>
      </Row>
      <Row index="69">
        <F>833</F>
      </Row>
      <Row index="70">
        <F>1127</F>
      </Row>
      <Row index="71">
        <F>833</F>
      </Row>
      <Row index="72">
        <F>931</F>
      </Row>
      <Row index="73">
        <F>833</F>
      </Row>
      <Row index="74">
        <F>784</F>
      </Row>
      <Row index="75">
        <F>392</F>
      </Row>
      <Row index="76">
        <F>931</F>
      </Row>
      <Row index="77">
        <F>637</F>
      </Row>
      <Row index="78">
        <F>833</F>
      </Row>
      <Row index="79">
        <F>637</F>
      </Row>
      <Row index="80">
        <F>1323</F>
      </Row>
      <Row index="81">
        <F>1127</F>
      </Row>
      <Row index="82">
        <F>833</F>
      </Row>
      <Row index="83">
        <F>1274</F>
      </Row>
      <Row index="84">
        <F>1470</F>
      </Row>
      <Row index="85">
        <F>1421</F>
      </Row>
      <Row index="86">
        <F>1617</F>
      </Row>
      <Row index="87">
        <F>1323</F>
      </Row>
      <Row index="88">
        <F>1225</F>
      </Row>
      <Row index="89">
        <F>1519</F>
      </Row>
      <Row index="90">
        <F>1274</F>
      </Row>
      <Row index="91">
        <F>1127</F>
      </Row>
      <Row index="92">
        <F>1421</F>
      </Row>
      <Row index="93">
        <F>833</F>
      </Row>
      <Row index="94">
        <F>1274</F>
      </Row>
      <Row index="95">
        <F>1911</F>
      </Row>
      <Row index="96">
        <F>1519</F>
      </Row>
      <Row index="97">
        <F>1911</F>
      </Row>
      <Row index="98">
        <F>1862</F>
      </Row>
      <Row index="99">
        <F>1617</F>
      </Row>
      <Row index="100">
        <F>1470</F>
      </Row>
      <Row index="101">
        <F>1274</F>
      </Row>
      <Row index="102">
        <F>2205</F>
      </Row>
      <Row index="103">
        <F>1715</F>
      </Row>
      <Row index="104">
        <F>1225</F>
      </Row>
      <Row index="105">
        <F>2352</F>
      </Row>
      <Row index="106">
        <F>1911</F>
      </Row>
      <Row index="107">
        <F>1911</F>
      </Row>
      <Row index="108">
        <F>2450</F>
      </Row>
      <Row index="109">
        <F>2156</F>
      </Row>
      <Row index="110">
        <F>2597</F>
      </Row>
      <Row index="111">
        <F>2058</F>
      </Row>
      <Row index="112">
        <F>2548</F>
      </Row>
      <Row index="113">
        <F>2303</F>
      </Row>
      <Row index="114">
        <F>2352</F>
      </Row>
      <Row index="115">
        <F>2940</F>
      </Row>
      <Row index="116">
        <F>2793</F>
      </Row>
      <Row index="117">
        <F>3283</F>
      </Row>
      <Row index="118">
        <F>2940</F>
      </Row>
      <Row index="119">
        <F>2646</F>
      </Row>
      <Row index="120">
        <F>2254</F>
      </Row>
      <Row index="121">
        <F>2940</F>
      </Row>
      <Row index="122">
        <F>3283</F>
      </Row>
      <Row index="123">
        <F>2597</F>
      </Row>
      <Row index="124">
        <F>3087</F>
      </Row>
      <Row index="125">
        <F>2548</F>
      </Row>
      <Row index="126">
        <F>2597</F>
      </Row>
      <Row index="127">
        <F>3332</F>
      </Row>
      <Row index="128">
        <F>3185</F>
      </Row>
      <Row index="129">
        <F>3283</F>
      </Row>
      <Row index="130">
        <F>3185</F>
      </Row>
      <Row index="131">
        <F>3577</F>
      </Row>
      <Row index="132">
        <F>3283</F>
      </Row>
      <Row index="133">
        <F>3773</F>
      </Row>
      <Row index="134">
        <F>3724</F>
      </Row>
      <Row index="135">
        <F>4557</F>
      </Row>
      <Row index="136">
        <F>4655</F>
      </Row>
      <Row index="137">
        <F>4802</F>
      </Row>
      <Row index="138">
        <F>4753</F>
      </Row>
      <Row index="139">
        <F>5292</F>
      </Row>
      <Row index="140">
        <F>5684</F>
      </Row>
      <Row index="141">
        <F>5929</F>
      </Row>
      <Row index="142">
        <F>5684</F>
      </Row>
      <Row index="143">
        <F>7007</F>
      </Row>
      <Row index="144">
        <F>6027</F>
      </Row>
      <Row index="145">
        <F>7791</F>
      </Row>
      <Row index="146">
        <F>9065</F>
      </Row>
      <Row index="147">
        <F>8624</F>
      </Row>
      <Row index="148">
        <F>10192</F>
      </Row>
      <Row index="149">
        <F>9408</F>
      </Row>
      <Row index="150">
        <F>9849</F>
      </Row>
      <Row index="151">
        <F>11025</F>
      </Row>
      <Row index="152">
        <F>11564</F>
      </Row>
      <Row index="153">
        <F>11711</F>
      </Row>
      <Row index="154">
        <F>10878</F>
      </Row>
      <Row index="155">
        <F>13867</F>
      </Row>
      <Row index="156">
        <F>12838</F>
      </Row>
      <Row index="157">
        <F>13671</F>
      </Row>
      <Row index="158">
        <F>13720</F>
      </Row>
      <Row index="159">
        <F>16219</F>
      </Row>
      <Row index="160">
        <F>18326</F>
      </Row>
      <Row index="161">
        <F>19796</F>
      </Row>
      <Row index="162">
        <F>18914</F>
      </Row>
      <Row index="163">
        <F>21168</F>
      </Row>
      <Row index="164">
        <F>19698</F>
      </Row>
      <Row index="165">
        <F>23373</F>
      </Row>
      <Row index="166">
        <F>23030</F>
      </Row>
      <Row index="167">
        <F>24304</F>
      </Row>
      <Row index="168">
        <F>27636</F>
      </Row>
      <Row index="169">
        <F>27881</F>
      </Row>
      <Row index="170">
        <F>31605</F>
      </Row>
      <Row index="171">
        <F>34790</F>
      </Row>
      <Row index="172">
        <F>37926</F>
      </Row>
      <Row index="173">
        <F>48020</F>
      </Row>
      <Row index="174">
        <F>51646</F>
      </Row>
      <Row index="175">
        <F>62426</F>
      </Row>
      <Row index="176">
        <F>77959</F>
      </Row>
      <Row index="177">
        <F>93198</F>
      </Row>
      <Row index="178">
        <F>115640</F>
      </Row>
      <Row index="179">
        <F>126126</F>
      </Row>
      <Row index="180">
        <F>144305</F>
      </Row>
      <Row index="181">
        <F>149891</F>
      </Row>
      <Row index="182">
        <F>163660</F>
      </Row>
      <Row index="183">
        <F>173754</F>
      </Row>
      <Row index="184">
        <F>183211</F>
      </Row>
      <Row index="185">
        <F>203693</F>
      </Row>
      <Row index="186">
        <F>232848</F>
      </Row>
      <Row index="187">
        <F>277830</F>
      </Row>
      <Row index="188">
        <F>339864</F>
      </Row>
      <Row index="189">
        <F>408513</F>
      </Row>
      <Row index="190">
        <F>487207</F>
      </Row>
      <Row index="191">
        <F>569674</F>
      </Row>
      <Row index="192">
        <F>599221</F>
      </Row>
      <Row index="193">
        <F>617988</F>
      </Row>
      <Row index="194">
        <F>619654</F>
      </Row>
      <Row index="195">
        <F>588637</F>
      </Row>
      <Row index="196">
        <F>554827</F>
      </Row>
      <Row index="197">
        <F>548751</F>
      </Row>
      <Row index="198">
        <F>529298</F>
      </Row>
      <Row index="199">
        <F>566832</F>
      </Row>
      <Row index="200">
        <F>703052</F>
      </Row>
      <Row index="201">
        <F>798700</F>
      </Row>
      <Row index="202">
        <F>631169</F>
      </Row>
      <Row index="203">
        <F>400575</F>
      </Row>
      <Row index="204">
        <F>232015</F>
      </Row>
      <Row index="205">
        <F>133868</F>
      </Row>
      <Row index="206">
        <F>91532</F>
      </Row>
      <Row index="207">
        <F>75999</F>
      </Row>
      <Row index="208">
        <F>62867</F>
      </Row>
      <Row index="209">
        <F>64386</F>
      </Row>
      <Row index="210">
        <F>63994</F>
      </Row>
      <Row index="211">
        <F>59878</F>
      </Row>
      <Row index="212">
        <F>65317</F>
      </Row>
      <Row index="213">
        <F>63553</F>
      </Row>
      <Row index="214">
        <F>62230</F>
      </Row>
      <Row index="215">
        <F>65660</F>
      </Row>
      <Row index="216">
        <F>66052</F>
      </Row>
      <Row index="217">
        <F>65072</F>
      </Row>
      <Row index="218">
        <F>66444</F>
      </Row>
      <Row index="219">
        <F>65170</F>
      </Row>
      <Row index="220">
        <F>65562</F>
      </Row>
      <Row index="221">
        <F>65562</F>
      </Row>
      <Row index="222">
        <F>69531</F>
      </Row>
      <Row index="223">
        <F>69041</F>
      </Row>
      <Row index="224">
        <F>68404</F>
      </Row>
      <Row index="225">
        <F>68845</F>
      </Row>
      <Row index="226">
        <F>71050</F>
      </Row>
      <Row index="227">
        <F>78351</F>
      </Row>
      <Row index="228">
        <F>75460</F>
      </Row>
      <Row index="229">
        <F>83153</F>
      </Row>
      <Row index="230">
        <F>80801</F>
      </Row>
      <Row index="231">
        <F>91287</F>
      </Row>
      <Row index="232">
        <F>90601</F>
      </Row>
      <Row index="233">
        <F>99813</F>
      </Row>
      <Row index="234">
        <F>100107</F>
      </Row>
      <Row index="235">
        <F>107065</F>
      </Row>
      <Row index="236">
        <F>107800</F>
      </Row>
      <Row index="237">
        <F>118041</F>
      </Row>
      <Row index="238">
        <F>112602</F>
      </Row>
      <Row index="239">
        <F>117747</F>
      </Row>
      <Row index="240">
        <F>113974</F>
      </Row>
      <Row index="241">
        <F>112112</F>
      </Row>
      <Row index="242">
        <F>120589</F>
      </Row>
      <Row index="243">
        <F>116669</F>
      </Row>
      <Row index="244">
        <F>115395</F>
      </Row>
      <Row index="245">
        <F>120638</F>
      </Row>
      <Row index="246">
        <F>118139</F>
      </Row>
      <Row index="247">
        <F>122549</F>
      </Row>
      <Row index="248">
        <F>122549</F>
      </Row>
      <Row index="249">
        <F>136367</F>
      </Row>
      <Row index="250">
        <F>136416</F>
      </Row>
      <Row index="251">
        <F>158564</F>
      </Row>
      <Row index="252">
        <F>206584</F>
      </Row>
      <Row index="253">
        <F>316540</F>
      </Row>
      <Row index="254">
        <F>549927</F>
      </Row>
      <Row index="255">
        <F>1918987</F>
      </Row>
    </GDALRasterAttributeTable>
    <Metadata>
      <MDI key="LAYER_TYPE">athematic</MDI>
      <MDI key="STATISTICS_HISTOBINVALUES">1049384|50666|16317|17346|24892|28861|16807|4753|1764|1764|1372|1176|637|588|1225|1127|1617|1519|1176|931|1715|1470|931|686|784|637|441|441|294|441|588|784|735|882|1029|833|735|735|980|441|637|931|980|1029|980|637|490|490|343|392|588|539|588|833|490|1127|980|931|490|686|441|588|441|784|441|637|343|637|882|833|1127|833|931|833|784|392|931|637|833|637|1323|1127|833|1274|1470|1421|1617|1323|1225|1519|1274|1127|1421|833|1274|1911|1519|1911|1862|1617|1470|1274|2205|1715|1225|2352|1911|1911|2450|2156|2597|2058|2548|2303|2352|2940|2793|3283|2940|2646|2254|2940|3283|2597|3087|2548|2597|3332|3185|3283|3185|3577|3283|3773|3724|4557|4655|4802|4753|5292|5684|5929|5684|7007|6027|7791|9065|8624|10192|9408|9849|11025|11564|11711|10878|13867|12838|13671|13720|16219|18326|19796|18914|21168|19698|23373|23030|24304|27636|27881|31605|34790|37926|48020|51646|62426|77959|93198|115640|126126|144305|149891|163660|173754|183211|203693|232848|277830|339864|408513|487207|569674|599221|617988|619654|588637|554827|548751|529298|566832|703052|798700|631169|400575|232015|133868|91532|75999|62867|64386|63994|59878|65317|63553|62230|65660|66052|65072|66444|65170|65562|65562|69531|69041|68404|68845|71050|78351|75460|83153|80801|91287|90601|99813|100107|107065|107800|118041|112602|117747|113974|112112|120589|116669|115395|120638|118139|122549|122549|136367|136416|158564|206584|316540|549927|1918987|</MDI>
    </Metadata>
  </PAMRasterBand>
  <PAMRasterBand band="2">
    <Histograms>
      <HistItem>
        <HistMin>-0.5</HistMin>
        <HistMax>255.5</HistMax>
        <BucketCount>256</BucketCount>
        <IncludeOutOfRange>0</IncludeOutOfRange>
        <Approximate>1</Approximate>
        <HistCounts>156|9|10|15|19|19|17|11|8|9|29|19|9|2|1|4|1|1|2|2|5|0|1|0|3|1|2|0|4|4|0|1|1|3|2|0|3|0|2|2|0|1|0|2|4|0|2|0|0|1|1|2|2|2|0|2|1|1|1|1|2|1|2|0|3|1|1|2|0|1|3|1|1|2|1|0|0|1|2|0|2|2|1|0|2|1|0|3|1|1|0|2|2|2|1|2|2|1|1|1|2|1|0|1|3|3|2|1|0|1|0|0|1|1|1|3|4|1|1|2|1|0|2|3|1|1|4|0|1|0|0|0|0|1|4|0|3|1|2|1|0|0|2|2|1|1|0|0|2|3|1|1|1|1|3|1|2|3|2|2|0|2|4|3|2|4|2|1|2|4|1|0|3|3|4|2|5|5|6|8|4|6|5|5|5|5|7|8|6|8|7|7|15|14|17|11|21|20|25|30|24|33|51|50|58|76|70|87|87|96|108|138|161|149|169|173|202|187|186|208|179|180|161|167|158|163|141|151|130|122|99|117|95|99|83|95|107|95|95|91|91|79|81|87|87|63|72|68|63|48|59|50|38|27|19|32</HistCounts>
      </HistItem>
    </Histograms>
    <GDALRasterAttributeTable>
      <FieldDefn index="0">
        <Name>Histogram</Name>
        <Type>0</Type>
        <Usage>0</Usage>
      </FieldDefn>
      <Row index="0">
        <F>1059968</F>
      </Row>
      <Row index="1">
        <F>34741</F>
      </Row>
      <Row index="2">
        <F>16415</F>
      </Row>
      <Row index="3">
        <F>15533</F>
      </Row>
      <Row index="4">
        <F>24941</F>
      </Row>
      <Row index="5">
        <F>31458</F>
      </Row>
      <Row index="6">
        <F>22540</F>
      </Row>
      <Row index="7">
        <F>5096</F>
      </Row>
      <Row index="8">
        <F>1764</F>
      </Row>
      <Row index="9">
        <F>931</F>
      </Row>
      <Row index="10">
        <F>1323</F>
      </Row>
      <Row index="11">
        <F>931</F>
      </Row>
      <Row index="12">
        <F>1225</F>
      </Row>
      <Row index="13">
        <F>1127</F>
      </Row>
      <Row index="14">
        <F>441</F>
      </Row>
      <Row index="15">
        <F>1029</F>
      </Row>
      <Row index="16">
        <F>1470</F>
      </Row>
      <Row index="17">
        <F>686</F>
      </Row>
      <Row index="18">
        <F>1813</F>
      </Row>
      <Row index="19">
        <F>2107</F>
      </Row>
      <Row index="20">
        <F>2401</F>
      </Row>
      <Row index="21">
        <F>1568</F>
      </Row>
      <Row index="22">
        <F>833</F>
      </Row>
      <Row index="23">
        <F>735</F>
      </Row>
      <Row index="24">
        <F>980</F>
      </Row>
      <Row index="25">
        <F>637</F>
      </Row>
      <Row index="26">
        <F>735</F>
      </Row>
      <Row index="27">
        <F>441</F>
      </Row>
      <Row index="28">
        <F>392</F>
      </Row>
      <Row index="29">
        <F>343</F>
      </Row>
      <Row index="30">
        <F>294</F>
      </Row>
      <Row index="31">
        <F>588</F>
      </Row>
      <Row index="32">
        <F>637</F>
      </Row>
      <Row index="33">
        <F>539</F>
      </Row>
      <Row index="34">
        <F>735</F>
      </Row>
      <Row index="35">
        <F>833</F>
      </Row>
      <Row index="36">
        <F>784</F>
      </Row>
      <Row index="37">
        <F>686</F>
      </Row>
      <Row index="38">
        <F>1029</F>
      </Row>
      <Row index="39">
        <F>1127</F>
      </Row>
      <Row index="40">
        <F>686</F>
      </Row>
      <Row index="41">
        <F>1372</F>
      </Row>
      <Row index="42">
        <F>1127</F>
      </Row>
      <Row index="43">
        <F>1519</F>
      </Row>
      <Row index="44">
        <F>1274</F>
      </Row>
      <Row index="45">
        <F>686</F>
      </Row>
      <Row index="46">
        <F>539</F>
      </Row>
      <Row index="47">
        <F>686</F>
      </Row>
      <Row index="48">
        <F>490</F>
      </Row>
      <Row index="49">
        <F>588</F>
      </Row>
      <Row index="50">
        <F>196</F>
      </Row>
      <Row index="51">
        <F>588</F>
      </Row>
      <Row index="52">
        <F>490</F>
      </Row>
      <Row index="53">
        <F>294</F>
      </Row>
      <Row index="54">
        <F>637</F>
      </Row>
      <Row index="55">
        <F>637</F>
      </Row>
      <Row index="56">
        <F>686</F>
      </Row>
      <Row index="57">
        <F>1029</F>
      </Row>
      <Row index="58">
        <F>392</F>
      </Row>
      <Row index="59">
        <F>931</F>
      </Row>
      <Row index="60">
        <F>784</F>
      </Row>
      <Row index="61">
        <F>490</F>
      </Row>
      <Row index="62">
        <F>1078</F>
      </Row>
      <Row index="63">
        <F>980</F>
      </Row>
      <Row index="64">
        <F>1078</F>
      </Row>
      <Row index="65">
        <F>1078</F>
      </Row>
      <Row index="66">
        <F>1323</F>
      </Row>
      <Row index="67">
        <F>1078</F>
      </Row>
      <Row index="68">
        <F>1617</F>
      </Row>
      <Row index="69">
        <F>1225</F>
      </Row>
      <Row index="70">
        <F>1225</F>
      </Row>
      <Row index="71">
        <F>1617</F>
      </Row>
      <Row index="72">
        <F>1176</F>
      </Row>
      <Row index="73">
        <F>1813</F>
      </Row>
      <Row index="74">
        <F>1519</F>
      </Row>
      <Row index="75">
        <F>1225</F>
      </Row>
      <Row index="76">
        <F>1568</F>
      </Row>
      <Row index="77">
        <F>1715</F>
      </Row>
      <Row index="78">
        <F>1323</F>
      </Row>
      <Row index="79">
        <F>1764</F>
      </Row>
      <Row index="80">
        <F>1519</F>
      </Row>
      <Row index="81">
        <F>1715</F>
      </Row>
      <Row index="82">
        <F>1568</F>
      </Row>
      <Row index="83">
        <F>1323</F>
      </Row>
      <Row index="84">
        <F>1274</F>
      </Row>
      <Row index="85">
        <F>1960</F>
      </Row>
      <Row index="86">
        <F>2205</F>
      </Row>
      <Row index="87">
        <F>1666</F>
      </Row>
      <Row index="88">
        <F>1519</F>
      </Row>
      <Row index="89">
        <F>1862</F>
      </Row>
      <Row index="90">
        <F>1421</F>
      </Row>
      <Row index="91">
        <F>2450</F>
      </Row>
      <Row index="92">
        <F>1568</F>
      </Row>
      <Row index="93">
        <F>2450</F>
      </Row>
      <Row index="94">
        <F>2107</F>
      </Row>
      <Row index="95">
        <F>2156</F>
      </Row>
      <Row index="96">
        <F>2793</F>
      </Row>
      <Row index="97">
        <F>2254</F>
      </Row>
      <Row index="98">
        <F>3038</F>
      </Row>
      <Row index="99">
        <F>2548</F>
      </Row>
      <Row index="100">
        <F>3577</F>
      </Row>
      <Row index="101">
        <F>2548</F>
      </Row>
      <Row index="102">
        <F>3087</F>
      </Row>
      <Row index="103">
        <F>2499</F>
      </Row>
      <Row index="104">
        <F>1813</F>
      </Row>
      <Row index="105">
        <F>2352</F>
      </Row>
      <Row index="106">
        <F>3479</F>
      </Row>
      <Row index="107">
        <F>2744</F>
      </Row>
      <Row index="108">
        <F>2793</F>
      </Row>
      <Row index="109">
        <F>2352</F>
      </Row>
      <Row index="110">
        <F>3871</F>
      </Row>
      <Row index="111">
        <F>1862</F>
      </Row>
      <Row index="112">
        <F>2499</F>
      </Row>
      <Row index="113">
        <F>3038</F>
      </Row>
      <Row index="114">
        <F>3283</F>
      </Row>
      <Row index="115">
        <F>2842</F>
      </Row>
      <Row index="116">
        <F>3136</F>
      </Row>
      <Row index="117">
        <F>2646</F>
      </Row>
      <Row index="118">
        <F>2793</F>
      </Row>
      <Row index="119">
        <F>2793</F>
      </Row>
      <Row index="120">
        <F>2940</F>
      </Row>
      <Row index="121">
        <F>3136</F>
      </Row>
      <Row index="122">
        <F>3528</F>
      </Row>
      <Row index="123">
        <F>3430</F>
      </Row>
      <Row index="124">
        <F>3087</F>
      </Row>
      <Row index="125">
        <F>3430</F>
      </Row>
      <Row index="126">
        <F>3528</F>
      </Row>
      <Row index="127">
        <F>3381</F>
      </Row>
      <Row index="128">
        <F>4802</F>
      </Row>
      <Row index="129">
        <F>4165</F>
      </Row>
      <Row index="130">
        <F>3185</F>
      </Row>
      <Row index="131">
        <F>3920</F>
      </Row>
      <Row index="132">
        <F>3626</F>
      </Row>
      <Row index="133">
        <F>3920</F>
      </Row>
      <Row index="134">
        <F>4312</F>
      </Row>
      <Row index="135">
        <F>4410</F>
      </Row>
      <Row index="136">
        <F>4606</F>
      </Row>
      <Row index="137">
        <F>5978</F>
      </Row>
      <Row index="138">
        <F>4557</F>
      </Row>
      <Row index="139">
        <F>4900</F>
      </Row>
      <Row index="140">
        <F>5145</F>
      </Row>
      <Row index="141">
        <F>4410</F>
      </Row>
      <Row index="142">
        <F>5831</F>
      </Row>
      <Row index="143">
        <F>5145</F>
      </Row>
      <Row index="144">
        <F>5929</F>
      </Row>
      <Row index="145">
        <F>5929</F>
      </Row>
      <Row index="146">
        <F>6321</F>
      </Row>
      <Row index="147">
        <F>6762</F>
      </Row>
      <Row index="148">
        <F>5047</F>
      </Row>
      <Row index="149">
        <F>6125</F>
      </Row>
      <Row index="150">
        <F>7301</F>
      </Row>
      <Row index="151">
        <F>7742</F>
      </Row>
      <Row index="152">
        <F>7546</F>
      </Row>
      <Row index="153">
        <F>7742</F>
      </Row>
      <Row index="154">
        <F>9016</F>
      </Row>
      <Row index="155">
        <F>8477</F>
      </Row>
      <Row index="156">
        <F>8624</F>
      </Row>
      <Row index="157">
        <F>9065</F>
      </Row>
      <Row index="158">
        <F>10780</F>
      </Row>
      <Row index="159">
        <F>10878</F>
      </Row>
      <Row index="160">
        <F>11662</F>
      </Row>
      <Row index="161">
        <F>12936</F>
      </Row>
      <Row index="162">
        <F>13377</F>
      </Row>
      <Row index="163">
        <F>14161</F>
      </Row>
      <Row index="164">
        <F>16072</F>
      </Row>
      <Row index="165">
        <F>15484</F>
      </Row>
      <Row index="166">
        <F>17640</F>
      </Row>
      <Row index="167">
        <F>19698</F>
      </Row>
      <Row index="168">
        <F>22050</F>
      </Row>
      <Row index="169">
        <F>23814</F>
      </Row>
      <Row index="170">
        <F>26607</F>
      </Row>
      <Row index="171">
        <F>27489</F>
      </Row>
      <Row index="172">
        <F>29204</F>
      </Row>
      <Row index="173">
        <F>33369</F>
      </Row>
      <Row index="174">
        <F>36848</F>
      </Row>
      <Row index="175">
        <F>40915</F>
      </Row>
      <Row index="176">
        <F>46158</F>
      </Row>
      <Row index="177">
        <F>48118</F>
      </Row>
      <Row index="178">
        <F>53018</F>
      </Row>
      <Row index="179">
        <F>56742</F>
      </Row>
      <Row index="180">
        <F>63651</F>
      </Row>
      <Row index="181">
        <F>64974</F>
      </Row>
      <Row index="182">
        <F>65464</F>
      </Row>
      <Row index="183">
        <F>73843</F>
      </Row>
      <Row index="184">
        <F>73647</F>
      </Row>
      <Row index="185">
        <F>76293</F>
      </Row>
      <Row index="186">
        <F>76048</F>
      </Row>
      <Row index="187">
        <F>82712</F>
      </Row>
      <Row index="188">
        <F>78792</F>
      </Row>
      <Row index="189">
        <F>80850</F>
      </Row>
      <Row index="190">
        <F>87857</F>
      </Row>
      <Row index="191">
        <F>87024</F>
      </Row>
      <Row index="192">
        <F>91679</F>
      </Row>
      <Row index="193">
        <F>95158</F>
      </Row>
      <Row index="194">
        <F>95158</F>
      </Row>
      <Row index="195">
        <F>98833</F>
      </Row>
      <Row index="196">
        <F>104223</F>
      </Row>
      <Row index="197">
        <F>111524</F>
      </Row>
      <Row index="198">
        <F>115101</F>
      </Row>
      <Row index="199">
        <F>119707</F>
      </Row>
      <Row index="200">
        <F>134162</F>
      </Row>
      <Row index="201">
        <F>137690</F>
      </Row>
      <Row index="202">
        <F>151949</F>
      </Row>
      <Row index="203">
        <F>162778</F>
      </Row>
      <Row index="204">
        <F>183015</F>
      </Row>
      <Row index="205">
        <F>192668</F>
      </Row>
      <Row index="206">
        <F>210357</F>
      </Row>
      <Row index="207">
        <F>231819</F>
      </Row>
      <Row index="208">
        <F>249900</F>
      </Row>
      <Row index="209">
        <F>271019</F>
      </Row>
      <Row index="210">
        <F>281456</F>
      </Row>
      <Row index="211">
        <F>290766</F>
      </Row>
      <Row index="212">
        <F>303114</F>
      </Row>
      <Row index="213">
        <F>309974</F>
      </Row>
      <Row index="214">
        <F>308210</F>
      </Row>
      <Row index="215">
        <F>314041</F>
      </Row>
      <Row index="216">
        <F>320852</F>
      </Row>
      <Row index="217">
        <F>311150</F>
      </Row>
      <Row index="218">
        <F>309386</F>
      </Row>
      <Row index="219">
        <F>306544</F>
      </Row>
      <Row index="220">
        <F>295960</F>
      </Row>
      <Row index="221">
        <F>303457</F>
      </Row>
      <Row index="222">
        <F>288855</F>
      </Row>
      <Row index="223">
        <F>297185</F>
      </Row>
      <Row index="224">
        <F>289492</F>
      </Row>
      <Row index="225">
        <F>283269</F>
      </Row>
      <Row index="226">
        <F>276997</F>
      </Row>
      <Row index="227">
        <F>284445</F>
      </Row>
      <Row index="228">
        <F>280868</F>
      </Row>
      <Row index="229">
        <F>283661</F>
      </Row>
      <Row index="230">
        <F>286454</F>
      </Row>
      <Row index="231">
        <F>319382</F>
      </Row>
      <Row index="232">
        <F>389746</F>
      </Row>
      <Row index="233">
        <F>519204</F>
      </Row>
      <Row index="234">
        <F>643860</F>
      </Row>
      <Row index="235">
        <F>465206</F>
      </Row>
      <Row index="236">
        <F>405475</F>
      </Row>
      <Row index="237">
        <F>353437</F>
      </Row>
      <Row index="238">
        <F>297087</F>
      </Row>
      <Row index="239">
        <F>251321</F>
      </Row>
      <Row index="240">
        <F>215551</F>
      </Row>
      <Row index="241">
        <F>191590</F>
      </Row>
      <Row index="242">
        <F>175028</F>
      </Row>
      <Row index="243">
        <F>162533</F>
      </Row>
      <Row index="244">
        <F>157535</F>
      </Row>
      <Row index="245">
        <F>147147</F>
      </Row>
      <Row index="246">
        <F>143325</F>
      </Row>
      <Row index="247">
        <F>146118</F>
      </Row>
      <Row index="248">
        <F>138180</F>
      </Row>
      <Row index="249">
        <F>143815</F>
      </Row>
      <Row index="250">
        <F>141904</F>
      </Row>
      <Row index="251">
        <F>156114</F>
      </Row>
      <Row index="252">
        <F>187229</F>
      </Row>
      <Row index="253">
        <F>296156</F>
      </Row>
      <Row index="254">
        <F>506121</F>
      </Row>
      <Row index="255">
        <F>1926680</F>
      </Row>
    </GDALRasterAttributeTable>
    <Metadata>
      <MDI key="LAYER_TYPE">athematic</MDI>
      <MDI key="STATISTICS_HISTOBINVALUES">1059968|34741|16415|15533|24941|31458|22540|5096|1764|931|1323|931|1225|1127|441|1029|1470|686|1813|2107|2401|1568|833|735|980|637|735|441|392|343|294|588|637|539|735|833|784|686|1029|1127|686|1372|1127|1519|1274|686|539|686|490|588|196|588|490|294|637|637|686|1029|392|931|784|490|1078|980|1078|1078|1323|1078|1617|1225|1225|1617|1176|1813|1519|1225|1568|1715|1323|1764|1519|1715|1568|1323|1274|1960|2205|1666|1519|1862|1421|2450|1568|2450|2107|2156|2793|2254|3038|2548|3577|2548|3087|2499|1813|2352|3479|2744|2793|2352|3871|1862|2499|3038|3283|2842|3136|2646|2793|2793|2940|3136|3528|3430|3087|3430|3528|3381|4802|4165|3185|3920|3626|3920|4312|4410|4606|5978|4557|4900|5145|4410|5831|5145|5929|5929|6321|6762|5047|6125|7301|7742|7546|7742|9016|8477|8624|9065|10780|10878|11662|12936|13377|14161|16072|15484|17640|19698|22050|23814|26607|27489|29204|33369|36848|40915|46158|48118|53018|56742|63651|64974|65464|73843|73647|76293|76048|82712|78792|80850|87857|87024|91679|95158|95158|98833|104223|111524|115101|119707|134162|137690|151949|162778|183015|192668|210357|231819|249900|271019|281456|290766|303114|309974|308210|314041|320852|311150|309386|306544|295960|303457|288855|297185|289492|283269|276997|284445|280868|283661|286454|319382|389746|519204|643860|465206|405475|353437|297087|251321|215551|191590|175028|162533|157535|147147|143325|146118|138180|143815|141904|156114|187229|296156|506121|1926680|</MDI>
    </Metadata>
  </PAMRasterBand>
  <PAMRasterBand band="3">
    <Histograms>
      <HistItem>
        <HistMin>-0.5</HistMin>
        <HistMax>255.5</HistMax>
        <BucketCount>256</BucketCount>
        <IncludeOutOfRange>0</IncludeOutOfRange>
        <Approximate>1</Approximate>
        <HistCounts>158|13|17|23|17|18|20|25|13|10|11|5|4|7|4|0|3|4|1|1|1|3|2|0|3|4|2|2|2|1|1|1|0|2|1|2|1|1|3|2|1|2|3|3|2|5|0|1|3|4|1|2|0|1|1|4|1|1|0|3|1|1|1|2|2|2|0|3|2|1|3|1|1|2|2|0|2|1|3|1|0|1|2|4|4|3|0|0|0|5|0|2|4|0|0|1|5|0|0|5|2|3|1|3|3|1|2|4|3|3|2|0|1|4|2|3|4|3|8|5|7|7|5|6|8|8|16|9|21|13|28|17|34|33|28|58|71|68|85|102|127|155|162|176|177|192|196|185|164|170|141|104|90|88|82|47|47|39|50|33|30|33|25|29|40|31|24|30|26|30|43|30|23|25|30|29|27|27|26|28|29|37|27|29|26|34|29|35|32|21|28|29|34|35|36|26|28|40|21|33|29|23|26|30|31|22|23|19|31|24|19|27|29|29|18|35|20|28|18|36|33|35|26|31|31|29|37|29|48|43|30|29|41|32|31|42|36|26|41|39|53|39|37|44|48|47|55|44|37|43|35|28|32|25|17|40</HistCounts>
      </HistItem>
    </Histograms>
    <GDALRasterAttributeTable>
      <FieldDefn index="0">
        <Name>Histogram</Name>
        <Type>0</Type>
        <Usage>0</Usage>
      </FieldDefn>
      <Row index="0">
        <F>1012291</F>
      </Row>
      <Row index="1">
        <F>85701</F>
      </Row>
      <Row index="2">
        <F>29057</F>
      </Row>
      <Row index="3">
        <F>24304</F>
      </Row>
      <Row index="4">
        <F>23716</F>
      </Row>
      <Row index="5">
        <F>17150</F>
      </Row>
      <Row index="6">
        <F>13818</F>
      </Row>
      <Row index="7">
        <F>5586</F>
      </Row>
      <Row index="8">
        <F>2254</F>
      </Row>
      <Row index="9">
        <F>1176</F>
      </Row>
      <Row index="10">
        <F>1470</F>
      </Row>
      <Row index="11">
        <F>1519</F>
      </Row>
      <Row index="12">
        <F>1617</F>
      </Row>
      <Row index="13">
        <F>1470</F>
      </Row>
      <Row index="14">
        <F>1421</F>
      </Row>
      <Row index="15">
        <F>1127</F>
      </Row>
      <Row index="16">
        <F>1372</F>
      </Row>
      <Row index="17">
        <F>1323</F>
      </Row>
      <Row index="18">
        <F>1078</F>
      </Row>
      <Row index="19">
        <F>1176</F>
      </Row>
      <Row index="20">
        <F>1960</F>
      </Row>
      <Row index="21">
        <F>1372</F>
      </Row>
      <Row index="22">
        <F>1029</F>
      </Row>
      <Row index="23">
        <F>882</F>
      </Row>
      <Row index="24">
        <F>1127</F>
      </Row>
      <Row index="25">
        <F>1176</F>
      </Row>
      <Row index="26">
        <F>1078</F>
      </Row>
      <Row index="27">
        <F>1176</F>
      </Row>
      <Row index="28">
        <F>833</F>
      </Row>
      <Row index="29">
        <F>539</F>
      </Row>
      <Row index="30">
        <F>931</F>
      </Row>
      <Row index="31">
        <F>833</F>
      </Row>
      <Row index="32">
        <F>784</F>
      </Row>
      <Row index="33">
        <F>588</F>
      </Row>
      <Row index="34">
        <F>686</F>
      </Row>
      <Row index="35">
        <F>588</F>
      </Row>
      <Row index="36">
        <F>1225</F>
      </Row>
      <Row index="37">
        <F>539</F>
      </Row>
      <Row index="38">
        <F>784</F>
      </Row>
      <Row index="39">
        <F>1127</F>
      </Row>
      <Row index="40">
        <F>833</F>
      </Row>
      <Row index="41">
        <F>1470</F>
      </Row>
      <Row index="42">
        <F>1813</F>
      </Row>
      <Row index="43">
        <F>1715</F>
      </Row>
      <Row index="44">
        <F>1617</F>
      </Row>
      <Row index="45">
        <F>980</F>
      </Row>
      <Row index="46">
        <F>1421</F>
      </Row>
      <Row index="47">
        <F>784</F>
      </Row>
      <Row index="48">
        <F>1029</F>
      </Row>
      <Row index="49">
        <F>1176</F>
      </Row>
      <Row index="50">
        <F>1225</F>
      </Row>
      <Row index="51">
        <F>1862</F>
      </Row>
      <Row index="52">
        <F>931</F>
      </Row>
      <Row index="53">
        <F>980</F>
      </Row>
      <Row index="54">
        <F>1323</F>
      </Row>
      <Row index="55">
        <F>980</F>
      </Row>
      <Row index="56">
        <F>1421</F>
      </Row>
      <Row index="57">
        <F>1519</F>
      </Row>
      <Row index="58">
        <F>1715</F>
      </Row>
      <Row index="59">
        <F>1372</F>
      </Row>
      <Row index="60">
        <F>1764</F>
      </Row>
      <Row index="61">
        <F>1666</F>
      </Row>
      <Row index="62">
        <F>2401</F>
      </Row>
      <Row index="63">
        <F>2303</F>
      </Row>
      <Row index="64">
        <F>2646</F>
      </Row>
      <Row index="65">
        <F>2842</F>
      </Row>
      <Row index="66">
        <F>2058</F>
      </Row>
      <Row index="67">
        <F>2695</F>
      </Row>
      <Row index="68">
        <F>3283</F>
      </Row>
      <Row index="69">
        <F>2597</F>
      </Row>
      <Row index="70">
        <F>2695</F>
      </Row>
      <Row index="71">
        <F>2940</F>
      </Row>
      <Row index="72">
        <F>3234</F>
      </Row>
      <Row index="73">
        <F>3332</F>
      </Row>
      <Row index="74">
        <F>3332</F>
      </Row>
      <Row index="75">
        <F>2989</F>
      </Row>
      <Row index="76">
        <F>3675</F>
      </Row>
      <Row index="77">
        <F>3038</F>
      </Row>
      <Row index="78">
        <F>3675</F>
      </Row>
      <Row index="79">
        <F>3920</F>
      </Row>
      <Row index="80">
        <F>3136</F>
      </Row>
      <Row index="81">
        <F>3626</F>
      </Row>
      <Row index="82">
        <F>3577</F>
      </Row>
      <Row index="83">
        <F>4018</F>
      </Row>
      <Row index="84">
        <F>4508</F>
      </Row>
      <Row index="85">
        <F>4067</F>
      </Row>
      <Row index="86">
        <F>3381</F>
      </Row>
      <Row index="87">
        <F>4949</F>
      </Row>
      <Row index="88">
        <F>4165</F>
      </Row>
      <Row index="89">
        <F>5194</F>
      </Row>
      <Row index="90">
        <F>4116</F>
      </Row>
      <Row index="91">
        <F>4459</F>
      </Row>
      <Row index="92">
        <F>5243</F>
      </Row>
      <Row index="93">
        <F>5782</F>
      </Row>
      <Row index="94">
        <F>5586</F>
      </Row>
      <Row index="95">
        <F>6419</F>
      </Row>
      <Row index="96">
        <F>6321</F>
      </Row>
      <Row index="97">
        <F>7252</F>
      </Row>
      <Row index="98">
        <F>7056</F>
      </Row>
      <Row index="99">
        <F>6174</F>
      </Row>
      <Row index="100">
        <F>8183</F>
      </Row>
      <Row index="101">
        <F>8085</F>
      </Row>
      <Row index="102">
        <F>9849</F>
      </Row>
      <Row index="103">
        <F>8869</F>
      </Row>
      <Row index="104">
        <F>10143</F>
      </Row>
      <Row index="105">
        <F>12446</F>
      </Row>
      <Row index="106">
        <F>14700</F>
      </Row>
      <Row index="107">
        <F>16317</F>
      </Row>
      <Row index="108">
        <F>18424</F>
      </Row>
      <Row index="109">
        <F>20727</F>
      </Row>
      <Row index="110">
        <F>24010</F>
      </Row>
      <Row index="111">
        <F>24353</F>
      </Row>
      <Row index="112">
        <F>29988</F>
      </Row>
      <Row index="113">
        <F>36946</F>
      </Row>
      <Row index="114">
        <F>42091</F>
      </Row>
      <Row index="115">
        <F>49294</F>
      </Row>
      <Row index="116">
        <F>53606</F>
      </Row>
      <Row index="117">
        <F>58457</F>
      </Row>
      <Row index="118">
        <F>66689</F>
      </Row>
      <Row index="119">
        <F>72765</F>
      </Row>
      <Row index="120">
        <F>75264</F>
      </Row>
      <Row index="121">
        <F>83496</F>
      </Row>
      <Row index="122">
        <F>84917</F>
      </Row>
      <Row index="123">
        <F>86142</F>
      </Row>
      <Row index="124">
        <F>90552</F>
      </Row>
      <Row index="125">
        <F>92659</F>
      </Row>
      <Row index="126">
        <F>97069</F>
      </Row>
      <Row index="127">
        <F>102508</F>
      </Row>
      <Row index="128">
        <F>105350</F>
      </Row>
      <Row index="129">
        <F>110544</F>
      </Row>
      <Row index="130">
        <F>114219</F>
      </Row>
      <Row index="131">
        <F>129409</F>
      </Row>
      <Row index="132">
        <F>144305</F>
      </Row>
      <Row index="133">
        <F>157878</F>
      </Row>
      <Row index="134">
        <F>176890</F>
      </Row>
      <Row index="135">
        <F>204379</F>
      </Row>
      <Row index="136">
        <F>232946</F>
      </Row>
      <Row index="137">
        <F>255731</F>
      </Row>
      <Row index="138">
        <F>282534</F>
      </Row>
      <Row index="139">
        <F>317618</F>
      </Row>
      <Row index="140">
        <F>342412</F>
      </Row>
      <Row index="141">
        <F>363041</F>
      </Row>
      <Row index="142">
        <F>360640</F>
      </Row>
      <Row index="143">
        <F>376369</F>
      </Row>
      <Row index="144">
        <F>374409</F>
      </Row>
      <Row index="145">
        <F>364021</F>
      </Row>
      <Row index="146">
        <F>363629</F>
      </Row>
      <Row index="147">
        <F>350693</F>
      </Row>
      <Row index="148">
        <F>334523</F>
      </Row>
      <Row index="149">
        <F>328545</F>
      </Row>
      <Row index="150">
        <F>312522</F>
      </Row>
      <Row index="151">
        <F>307573</F>
      </Row>
      <Row index="152">
        <F>303800</F>
      </Row>
      <Row index="153">
        <F>307769</F>
      </Row>
      <Row index="154">
        <F>338198</F>
      </Row>
      <Row index="155">
        <F>394156</F>
      </Row>
      <Row index="156">
        <F>498232</F>
      </Row>
      <Row index="157">
        <F>557963</F>
      </Row>
      <Row index="158">
        <F>456631</F>
      </Row>
      <Row index="159">
        <F>355201</F>
      </Row>
      <Row index="160">
        <F>269892</F>
      </Row>
      <Row index="161">
        <F>196980</F>
      </Row>
      <Row index="162">
        <F>139209</F>
      </Row>
      <Row index="163">
        <F>99764</F>
      </Row>
      <Row index="164">
        <F>71099</F>
      </Row>
      <Row index="165">
        <F>51107</F>
      </Row>
      <Row index="166">
        <F>43071</F>
      </Row>
      <Row index="167">
        <F>35721</F>
      </Row>
      <Row index="168">
        <F>35084</F>
      </Row>
      <Row index="169">
        <F>35525</F>
      </Row>
      <Row index="170">
        <F>31703</F>
      </Row>
      <Row index="171">
        <F>32536</F>
      </Row>
      <Row index="172">
        <F>30576</F>
      </Row>
      <Row index="173">
        <F>30527</F>
      </Row>
      <Row index="174">
        <F>32242</F>
      </Row>
      <Row index="175">
        <F>30919</F>
      </Row>
      <Row index="176">
        <F>32438</F>
      </Row>
      <Row index="177">
        <F>30086</F>
      </Row>
      <Row index="178">
        <F>29694</F>
      </Row>
      <Row index="179">
        <F>35966</F>
      </Row>
      <Row index="180">
        <F>35231</F>
      </Row>
      <Row index="181">
        <F>35721</F>
      </Row>
      <Row index="182">
        <F>35819</F>
      </Row>
      <Row index="183">
        <F>36848</F>
      </Row>
      <Row index="184">
        <F>34006</F>
      </Row>
      <Row index="185">
        <F>37093</F>
      </Row>
      <Row index="186">
        <F>39200</F>
      </Row>
      <Row index="187">
        <F>37387</F>
      </Row>
      <Row index="188">
        <F>38465</F>
      </Row>
      <Row index="189">
        <F>37534</F>
      </Row>
      <Row index="190">
        <F>37289</F>
      </Row>
      <Row index="191">
        <F>37730</F>
      </Row>
      <Row index="192">
        <F>40229</F>
      </Row>
      <Row index="193">
        <F>38416</F>
      </Row>
      <Row index="194">
        <F>37338</F>
      </Row>
      <Row index="195">
        <F>38514</F>
      </Row>
      <Row index="196">
        <F>40131</F>
      </Row>
      <Row index="197">
        <F>39788</F>
      </Row>
      <Row index="198">
        <F>38367</F>
      </Row>
      <Row index="199">
        <F>38857</F>
      </Row>
      <Row index="200">
        <F>41356</F>
      </Row>
      <Row index="201">
        <F>42385</F>
      </Row>
      <Row index="202">
        <F>40180</F>
      </Row>
      <Row index="203">
        <F>39690</F>
      </Row>
      <Row index="204">
        <F>40376</F>
      </Row>
      <Row index="205">
        <F>41013</F>
      </Row>
      <Row index="206">
        <F>40229</F>
      </Row>
      <Row index="207">
        <F>37926</F>
      </Row>
      <Row index="208">
        <F>43267</F>
      </Row>
      <Row index="209">
        <F>41993</F>
      </Row>
      <Row index="210">
        <F>45178</F>
      </Row>
      <Row index="211">
        <F>44149</F>
      </Row>
      <Row index="212">
        <F>48608</F>
      </Row>
      <Row index="213">
        <F>46844</F>
      </Row>
      <Row index="214">
        <F>49392</F>
      </Row>
      <Row index="215">
        <F>48461</F>
      </Row>
      <Row index="216">
        <F>52038</F>
      </Row>
      <Row index="217">
        <F>51303</F>
      </Row>
      <Row index="218">
        <F>58604</F>
      </Row>
      <Row index="219">
        <F>55713</F>
      </Row>
      <Row index="220">
        <F>60368</F>
      </Row>
      <Row index="221">
        <F>64141</F>
      </Row>
      <Row index="222">
        <F>64925</F>
      </Row>
      <Row index="223">
        <F>67718</F>
      </Row>
      <Row index="224">
        <F>69433</F>
      </Row>
      <Row index="225">
        <F>71148</F>
      </Row>
      <Row index="226">
        <F>71148</F>
      </Row>
      <Row index="227">
        <F>71736</F>
      </Row>
      <Row index="228">
        <F>74431</F>
      </Row>
      <Row index="229">
        <F>71834</F>
      </Row>
      <Row index="230">
        <F>72226</F>
      </Row>
      <Row index="231">
        <F>72618</F>
      </Row>
      <Row index="232">
        <F>77322</F>
      </Row>
      <Row index="233">
        <F>73157</F>
      </Row>
      <Row index="234">
        <F>74823</F>
      </Row>
      <Row index="235">
        <F>72961</F>
      </Row>
      <Row index="236">
        <F>72716</F>
      </Row>
      <Row index="237">
        <F>74480</F>
      </Row>
      <Row index="238">
        <F>70413</F>
      </Row>
      <Row index="239">
        <F>72079</F>
      </Row>
      <Row index="240">
        <F>71932</F>
      </Row>
      <Row index="241">
        <F>72422</F>
      </Row>
      <Row index="242">
        <F>74921</F>
      </Row>
      <Row index="243">
        <F>78449</F>
      </Row>
      <Row index="244">
        <F>78694</F>
      </Row>
      <Row index="245">
        <F>78155</F>
      </Row>
      <Row index="246">
        <F>83545</F>
      </Row>
      <Row index="247">
        <F>91385</F>
      </Row>
      <Row index="248">
        <F>92463</F>
      </Row>
      <Row index="249">
        <F>107310</F>
      </Row>
      <Row index="250">
        <F>120099</F>
      </Row>
      <Row index="251">
        <F>152488</F>
      </Row>
      <Row index="252">
        <F>204428</F>
      </Row>
      <Row index="253">
        <F>292481</F>
      </Row>
      <Row index="254">
        <F>430367</F>
      </Row>
      <Row index="255">
        <F>1783110</F>
      </Row>
    </GDALRasterAttributeTable>
    <Metadata>
      <MDI key="LAYER_TYPE">athematic</MDI>
      <MDI key="STATISTICS_HISTOBINVALUES">1012291|85701|29057|24304|23716|17150|13818|5586|2254|1176|1470|1519|1617|1470|1421|1127|1372|1323|1078|1176|1960|1372|1029|882|1127|1176|1078|1176|833|539|931|833|784|588|686|588|1225|539|784|1127|833|1470|1813|1715|1617|980|1421|784|1029|1176|1225|1862|931|980|1323|980|1421|1519|1715|1372|1764|1666|2401|2303|2646|2842|2058|2695|3283|2597|2695|2940|3234|3332|3332|2989|3675|3038|3675|3920|3136|3626|3577|4018|4508|4067|3381|4949|4165|5194|4116|4459|5243|5782|5586|6419|6321|7252|7056|6174|8183|8085|9849|8869|10143|12446|14700|16317|18424|20727|24010|24353|29988|36946|42091|49294|53606|58457|66689|72765|75264|83496|84917|86142|90552|92659|97069|102508|105350|110544|114219|129409|144305|157878|176890|204379|232946|255731|282534|317618|342412|363041|360640|376369|374409|364021|363629|350693|334523|328545|312522|307573|303800|307769|338198|394156|498232|557963|456631|355201|269892|196980|139209|99764|71099|51107|43071|35721|35084|35525|31703|32536|30576|30527|32242|30919|32438|30086|29694|35966|35231|35721|35819|36848|34006|37093|39200|37387|38465|37534|37289|37730|40229|38416|37338|38514|40131|39788|38367|38857|41356|42385|40180|39690|40376|41013|40229|37926|43267|41993|45178|44149|48608|46844|49392|48461|52038|51303|58604|55713|60368|64141|64925|67718|69433|71148|71148|71736|74431|71834|72226|72618|77322|73157|74823|72961|72716|74480|70413|72079|71932|72422|74921|78449|78694|78155|83545|91385|92463|107310|120099|152488|204428|292481|430367|1783110|</MDI>
    </Metadata>
  </PAMRasterBand>
</PAMDataset>
